blackman_client/__init__.py
blackman_client/api_client.py
blackman_client/api_response.py
blackman_client/configuration.py
blackman_client/exceptions.py
blackman_client/py.typed
blackman_client/rest.py
blackman_client/api/__init__.py
blackman_client/api/completions_api.py
blackman_client/api/feedback_api.py
blackman_client/api/semantic_cache_api.py
blackman_client/models/__init__.py
blackman_client/models/choice.py
blackman_client/models/completion_options.py
blackman_client/models/completion_request.py
blackman_client/models/completion_response.py
blackman_client/models/invalidate_response.py
blackman_client/models/message.py
blackman_client/models/provider.py
blackman_client/models/semantic_cache_config.py
blackman_client/models/semantic_cache_stats.py
blackman_client/models/submit_feedback_request.py
blackman_client/models/submit_feedback_response.py
blackman_client/models/usage.py
blackman_client-0.0.5.dist-info/licenses/LICENSE
blackman_client-0.0.5.dist-info/METADATA
blackman_client-0.0.5.dist-info/WHEEL
blackman_client-0.0.5.dist-info/top_level.txt
blackman_client-0.0.5.dist-info/RECORD
