Metadata-Version: 2.4
Name: blackman_client
Version: 0.0.5
Summary: Blackman AI API
Home-page: https://github.com/blackman-ai/python-sdk
Author: Blackman AI
Author-email: Blackman AI Support <team@openapitools.org>
License-Expression: MIT
Project-URL: Repository, https://github.com/GIT_USER_ID/GIT_REPO_ID
Keywords: OpenAPI,OpenAPI-Generator,Blackman AI API
Requires-Python: >=3.7
License-File: LICENSE
Requires-Dist: urllib3<3.0.0,>=2.1.0
Requires-Dist: python-dateutil>=2.8.2
Requires-Dist: pydantic>=2
Requires-Dist: typing-extensions>=4.7.1
Dynamic: author
Dynamic: home-page
Dynamic: license-file
Dynamic: requires-python
